[{"chSymbol": "JUNIORBEES", "chSeries": "EQ", "chPreviousClsPrice": 751.04, "chOpeningPrice": 755, "chTradeHighPrice": 755, "chTradeLowPrice": 737.21, "chLastTradedPrice": 740.5, "chClosingPrice": 740.89, "vwap": 741.11, "chTotTradedQty": 394474, "chTotTradedVal": 292349370.53, "chTotalTrades": 12189, "ch52WeekHighPrice": 777, "ch52WeekLowPrice": 595, "mtimestamp": "13-Feb-2026"}, {"chSymbol": "JUNIORBEES", "chSeries": "EQ", "chPreviousClsPrice": 753.85, "chOpeningPrice": 757.78, "chTradeHighPrice": 757.78, "chTradeLowPrice": 747.55, "chLastTradedPrice": 751, "chClosingPrice": 751.04, "vwap": 750.2, "chTotTradedQty": 248297, "chTotTradedVal": 186272026.52, "chTotalTrades": 8604, "ch52WeekHighPrice": 777, "ch52WeekLowPrice": 595, "mtimestamp": "12-Feb-2026"}, {"chSymbol": "JUNIORBEES", "chSeries": "EQ", "chPreviousClsPrice": 751.61, "chOpeningPrice": 756.87, "chTradeHighPrice": 756.87, "chTradeLowPrice": 749.02, "chLastTradedPrice": 753.6, "chClosingPrice": 753.85, "vwap": 752.29, "chTotTradedQty": 444562, "chTotTradedVal": 334437454.94, "chTotalTrades": 7609, "ch52WeekHighPrice": 777, "ch52WeekLowPrice": 595, "mtimestamp": "11-Feb-2026"}, {"chSymbol": "JUNIORBEES", "chSeries": "EQ", "chPreviousClsPrice": 748.66, "chOpeningPrice": 748.66, "chTradeHighPrice": 752.76, "chTradeLowPrice": 747.7, "chLastTradedPrice": 750.7, "chClosingPrice": 751.61, "vwap": 750.93, "chTotTradedQty": 393463, "chTotTradedVal": 295463727.55, "chTotalTrades": 9548, "ch52WeekHighPrice": 777, "ch52WeekLowPrice": 595, "mtimestamp": "10-Feb-2026"}, {"chSymbol": "JUNIORBEES", "chSeries": "EQ", "chPreviousClsPrice": 742.19, "chOpeningPrice": 748, "chTradeHighPrice": 749.25, "chTradeLowPrice": 738, "chLastTradedPrice": 748.2, "chClosingPrice": 748.66, "vwap": 747.12, "chTotTradedQty": 483720, "chTotTradedVal": 361398051.03, "chTotalTrades": 13706, "ch52WeekHighPrice": 777, "ch52WeekLowPrice": 595, "mtimestamp": "09-Feb-2026"}, {"chSymbol": "JUNIORBEES", "chSeries": "EQ", "chPreviousClsPrice": 740.33, "chOpeningPrice": 745, "chTradeHighPrice": 745, "chTradeLowPrice": 733, "chLastTradedPrice": 740.89, "chClosingPrice": 742.19, "vwap": 737.37, "chTotTradedQty": 503509, "chTotTradedVal": 371270832.13, "chTotalTrades": 9866, "ch52WeekHighPrice": 777, "ch52WeekLowPrice": 595, "mtimestamp": "06-Feb-2026"}, {"chSymbol": "JUNIORBEES", "chSeries": "EQ", "chPreviousClsPrice": 744.05, "chOpeningPrice": 748, "chTradeHighPrice": 748, "chTradeLowPrice": 735.6, "chLastTradedPrice": 739.97, "chClosingPrice": 740.33, "vwap": 738.92, "chTotTradedQty": 472540, "chTotTradedVal": 349170187.26, "chTotalTrades": 13972, "ch52WeekHighPrice": 777, "ch52WeekLowPrice": 595, "mtimestamp": "05-Feb-2026"}, {"chSymbol": "JUNIORBEES", "chSeries": "EQ", "chPreviousClsPrice": 738.79, "chOpeningPrice": 743, "chTradeHighPrice": 744.89, "chTradeLowPrice": 730.6, "chLastTradedPrice": 744.21, "chClosingPrice": 744.05, "vwap": 741.54, "chTotTradedQty": 425652, "chTotTradedVal": 315637471.15, "chTotalTrades": 9765, "ch52WeekHighPrice": 777, "ch52WeekLowPrice": 595, "mtimestamp": "04-Feb-2026"}, {"chSymbol": "JUNIORBEES", "chSeries": "EQ", "chPreviousClsPrice": 721.21, "chOpeningPrice": 739.67, "chTradeHighPrice": 749.19, "chTradeLowPrice": 735, "chLastTradedPrice": 739, "chClosingPrice": 738.79, "vwap": 739.42, "chTotTradedQty": 697688, "chTotTradedVal": 515883379.59, "chTotalTrades": 15228, "ch52WeekHighPrice": 777, "ch52WeekLowPrice": 595, "mtimestamp": "03-Feb-2026"}, {"chSymbol": "JUNIORBEES", "chSeries": "EQ", "chPreviousClsPrice": 718.13, "chOpeningPrice": 721.22, "chTradeHighPrice": 723, "chTradeLowPrice": 705.73, "chLastTradedPrice": 722.3, "chClosingPrice": 721.21, "vwap": 713.47, "chTotTradedQty": 581845, "chTotTradedVal": 415129256.31, "chTotalTrades": 22970, "ch52WeekHighPrice": 777, "ch52WeekLowPrice": 595, "mtimestamp": "02-Feb-2026"}, {"chSymbol": "JUNIORBEES", "chSeries": "EQ", "chPreviousClsPrice": 729.61, "chOpeningPrice": 747.5, "chTradeHighPrice": 747.5, "chTradeLowPrice": 704.71, "chLastTradedPrice": 723.89, "chClosingPrice": 718.13, "vwap": 721.13, "chTotTradedQty": 622890, "chTotTradedVal": 449184388.91, "chTotalTrades": 20548, "ch52WeekHighPrice": 777, "ch52WeekLowPrice": 595, "mtimestamp": "01-Feb-2026"}, {"chSymbol": "JUNIORBEES", "chSeries": "EQ", "chPreviousClsPrice": 733.95, "chOpeningPrice": 735.95, "chTradeHighPrice": 735.95, "chTradeLowPrice": 725.05, "chLastTradedPrice": 728, "chClosingPrice": 729.61, "vwap": 728.92, "chTotTradedQty": 780267, "chTotTradedVal": 568751626.27, "chTotalTrades": 12464, "ch52WeekHighPrice": 777, "ch52WeekLowPrice": 595, "mtimestamp": "30-Jan-2026"}, {"chSymbol": "JUNIORBEES", "chSeries": "EQ", "chPreviousClsPrice": 732, "chOpeningPrice": 729, "chTradeHighPrice": 734.81, "chTradeLowPrice": 727.29, "chLastTradedPrice": 734.3, "chClosingPrice": 733.95, "vwap": 731.97, "chTotTradedQty": 428250, "chTotTradedVal": 313464682.81, "chTotalTrades": 9278, "ch52WeekHighPrice": 777, "ch52WeekLowPrice": 595, "mtimestamp": "29-Jan-2026"}, {"chSymbol": "JUNIORBEES", "chSeries": "EQ", "chPreviousClsPrice": 717.06, "chOpeningPrice": 715, "chTradeHighPrice": 733, "chTradeLowPrice": 715, "chLastTradedPrice": 732.7, "chClosingPrice": 732, "vwap": 726.27, "chTotTradedQty": 499784, "chTotTradedVal": 362978762.02, "chTotalTrades": 9946, "ch52WeekHighPrice": 777, "ch52WeekLowPrice": 595, "mtimestamp": "28-Jan-2026"}, {"chSymbol": "JUNIORBEES", "chSeries": "EQ", "chPreviousClsPrice": 713.3, "chOpeningPrice": 714.82, "chTradeHighPrice": 719, "chTradeLowPrice": 709.2, "chLastTradedPrice": 719, "chClosingPrice": 717.06, "vwap": 713.59, "chTotTradedQty": 643370, "chTotTradedVal": 459103333.68, "chTotalTrades": 20821, "ch52WeekHighPrice": 777, "ch52WeekLowPrice": 595, "mtimestamp": "27-Jan-2026"}, {"chSymbol": "JUNIORBEES", "chSeries": "EQ", "chPreviousClsPrice": 727.47, "chOpeningPrice": 730.8, "chTradeHighPrice": 730.8, "chTradeLowPrice": 711.01, "chLastTradedPrice": 715, "chClosingPrice": 713.3, "vwap": 718.74, "chTotTradedQty": 585613, "chTotTradedVal": 420903244.37, "chTotalTrades": 16715, "ch52WeekHighPrice": 777, "ch52WeekLowPrice": 595, "mtimestamp": "23-Jan-2026"}, {"chSymbol": "JUNIORBEES", "chSeries": "EQ", "chPreviousClsPrice": 719.09, "chOpeningPrice": 722, "chTradeHighPrice": 730.9, "chTradeLowPrice": 716.59, "chLastTradedPrice": 728.3, "chClosingPrice": 727.47, "vwap": 726.88, "chTotTradedQty": 284206, "chTotTradedVal": 206582784.8, "chTotalTrades": 8394, "ch52WeekHighPrice": 777, "ch52WeekLowPrice": 595, "mtimestamp": "22-Jan-2026"}, {"chSymbol": "JUNIORBEES", "chSeries": "EQ", "chPreviousClsPrice": 722.64, "chOpeningPrice": 725, "chTradeHighPrice": 725.02, "chTradeLowPrice": 710.17, "chLastTradedPrice": 720.26, "chClosingPrice": 719.09, "vwap": 717.36, "chTotTradedQty": 760440, "chTotTradedVal": 545508752.46, "chTotalTrades": 17172, "ch52WeekHighPrice": 777, "ch52WeekLowPrice": 595, "mtimestamp": "21-Jan-2026"}, {"chSymbol": "JUNIORBEES", "chSeries": "EQ", "chPreviousClsPrice": 738.63, "chOpeningPrice": 738.63, "chTradeHighPrice": 741.15, "chTradeLowPrice": 720.01, "chLastTradedPrice": 726.95, "chClosingPrice": 722.64, "vwap": 728.01, "chTotTradedQty": 781740, "chTotTradedVal": 569117656.47, "chTotalTrades": 23765, "ch52WeekHighPrice": 777, "ch52WeekLowPrice": 595, "mtimestamp": "20-Jan-2026"}, {"chSymbol": "JUNIORBEES", "chSeries": "EQ", "chPreviousClsPrice": 740.69, "chOpeningPrice": 742.08, "chTradeHighPrice": 744.5, "chTradeLowPrice": 737, "chLastTradedPrice": 737.7, "chClosingPrice": 738.63, "vwap": 739.86, "chTotTradedQty": 546844, "chTotTradedVal": 404585499.67, "chTotalTrades": 14237, "ch52WeekHighPrice": 777, "ch52WeekLowPrice": 595, "mtimestamp": "19-Jan-2026"}, {"chSymbol": "JUNIORBEES", "chSeries": "EQ", "chPreviousClsPrice": 741.31, "chOpeningPrice": 744, "chTradeHighPrice": 746.49, "chTradeLowPrice": 736.7, "chLastTradedPrice": 740.6, "chClosingPrice": 740.69, "vwap": 742.1, "chTotTradedQty": 494936, "chTotTradedVal": 367289535.39, "chTotalTrades": 11520, "ch52WeekHighPrice": 777, "ch52WeekLowPrice": 595, "mtimestamp": "16-Jan-2026"}, {"chSymbol": "JUNIORBEES", "chSeries": "EQ", "chPreviousClsPrice": 737.06, "chOpeningPrice": 740, "chTradeHighPrice": 745, "chTradeLowPrice": 733.76, "chLastTradedPrice": 744.91, "chClosingPrice": 741.31, "vwap": 740.46, "chTotTradedQty": 465966, "chTotTradedVal": 345031428.03, "chTotalTrades": 8600, "ch52WeekHighPrice": 777, "ch52WeekLowPrice": 595, "mtimestamp": "14-Jan-2026"}, {"chSymbol": "JUNIORBEES", "chSeries": "EQ", "chPreviousClsPrice": 738.67, "chOpeningPrice": 740.67, "chTradeHighPrice": 743.84, "chTradeLowPrice": 731.35, "chLastTradedPrice": 736.79, "chClosingPrice": 737.06, "vwap": 736.6, "chTotTradedQty": 516660, "chTotTradedVal": 380572354.67, "chTotalTrades": 15220, "ch52WeekHighPrice": 777, "ch52WeekLowPrice": 595, "mtimestamp": "13-Jan-2026"}, {"chSymbol": "JUNIORBEES", "chSeries": "EQ", "chPreviousClsPrice": 737.32, "chOpeningPrice": 740, "chTradeHighPrice": 740, "chTradeLowPrice": 728.06, "chLastTradedPrice": 740, "chClosingPrice": 738.67, "vwap": 733.58, "chTotTradedQty": 722511, "chTotTradedVal": 530023127.3, "chTotalTrades": 19416, "ch52WeekHighPrice": 777, "ch52WeekLowPrice": 595, "mtimestamp": "12-Jan-2026"}, {"chSymbol": "JUNIORBEES", "chSeries": "EQ", "chPreviousClsPrice": 744.78, "chOpeningPrice": 747, "chTradeHighPrice": 748.3, "chTradeLowPrice": 734.71, "chLastTradedPrice": 737.5, "chClosingPrice": 737.32, "vwap": 740.07, "chTotTradedQty": 517148, "chTotTradedVal": 382723707.18, "chTotalTrades": 16169, "ch52WeekHighPrice": 777, "ch52WeekLowPrice": 595, "mtimestamp": "09-Jan-2026"}, {"chSymbol": "JUNIORBEES", "chSeries": "EQ", "chPreviousClsPrice": 760.84, "chOpeningPrice": 762.44, "chTradeHighPrice": 762.44, "chTradeLowPrice": 743.41, "chLastTradedPrice": 744.1, "chClosingPrice": 744.78, "vwap": 749.35, "chTotTradedQty": 565734, "chTotTradedVal": 423931147.8, "chTotalTrades": 19155, "ch52WeekHighPrice": 777, "ch52WeekLowPrice": 595, "mtimestamp": "08-Jan-2026"}, {"chSymbol": "JUNIORBEES", "chSeries": "EQ", "chPreviousClsPrice": 759.85, "chOpeningPrice": 759, "chTradeHighPrice": 762.99, "chTradeLowPrice": 756.86, "chLastTradedPrice": 760.5, "chClosingPrice": 760.84, "vwap": 759.93, "chTotTradedQty": 424559, "chTotTradedVal": 322634866.62, "chTotalTrades": 13168, "ch52WeekHighPrice": 777, "ch52WeekLowPrice": 595, "mtimestamp": "07-Jan-2026"}, {"chSymbol": "JUNIORBEES", "chSeries": "EQ", "chPreviousClsPrice": 756.12, "chOpeningPrice": 760, "chTradeHighPrice": 760.31, "chTradeLowPrice": 752.05, "chLastTradedPrice": 759.9, "chClosingPrice": 759.85, "vwap": 758.32, "chTotTradedQty": 778747, "chTotTradedVal": 590540684.62, "chTotalTrades": 39368, "ch52WeekHighPrice": 777, "ch52WeekLowPrice": 595, "mtimestamp": "06-Jan-2026"}, {"chSymbol": "JUNIORBEES", "chSeries": "EQ", "chPreviousClsPrice": 755.86, "chOpeningPrice": 760.08, "chTradeHighPrice": 760.08, "chTradeLowPrice": 752.78, "chLastTradedPrice": 755.91, "chClosingPrice": 756.12, "vwap": 756.04, "chTotTradedQty": 405269, "chTotTradedVal": 306400952.72, "chTotalTrades": 18188, "ch52WeekHighPrice": 777, "ch52WeekLowPrice": 595, "mtimestamp": "05-Jan-2026"}, {"chSymbol": "JUNIORBEES", "chSeries": "EQ", "chPreviousClsPrice": 747.76, "chOpeningPrice": 750, "chTradeHighPrice": 765, "chTradeLowPrice": 747.69, "chLastTradedPrice": 756, "chClosingPrice": 755.86, "vwap": 753.27, "chTotTradedQty": 426982, "chTotTradedVal": 321631762.12, "chTotalTrades": 12273, "ch52WeekHighPrice": 777, "ch52WeekLowPrice": 595, "mtimestamp": "02-Jan-2026"}, {"chSymbol": "JUNIORBEES", "chSeries": "EQ", "chPreviousClsPrice": 744.88, "chOpeningPrice": 745.4, "chTradeHighPrice": 748.47, "chTradeLowPrice": 743.52, "chLastTradedPrice": 747.43, "chClosingPrice": 747.76, "vwap": 746.34, "chTotTradedQty": 232825, "chTotTradedVal": 173765823.23, "chTotalTrades": 10386, "ch52WeekHighPrice": 777, "ch52WeekLowPrice": 595, "mtimestamp": "01-Jan-2026"}]